sphinx_design/__init__.py
sphinx_design/_compat.py
sphinx_design/article_info.py
sphinx_design/badges_buttons.py
sphinx_design/cards.py
sphinx_design/dropdown.py
sphinx_design/extension.py
sphinx_design/grids.py
sphinx_design/icons.py
sphinx_design/py.typed
sphinx_design/shared.py
sphinx_design/tabs.py
sphinx_design/compiled/__init__.py
sphinx_design/compiled/material-icons_LICENSE
sphinx_design/compiled/material-icons_VERSION.txt
sphinx_design/compiled/material_outlined.json
sphinx_design/compiled/material_regular.json
sphinx_design/compiled/material_round.json
sphinx_design/compiled/material_sharp.json
sphinx_design/compiled/material_twotone.json
sphinx_design/compiled/octicon_LICENSE
sphinx_design/compiled/octicons.json
sphinx_design/compiled/sd_tabs.js
sphinx_design/compiled/style.min.css
sphinx_design2-0.4.0.dist-info/LICENSE
sphinx_design2-0.4.0.dist-info/WHEEL
sphinx_design2-0.4.0.dist-info/METADATA
sphinx_design2-0.4.0.dist-info/RECORD
