Metadata-Version: 2.1
Name: sphinx-design2
Version: 0.4.0
Summary: A sphinx extension for designing beautiful, view size responsive web components.
Keywords: sphinx,extension,material design,web components
Author-email: Chris Sewell <chrisj_sewell@hotmail.com>
Requires-Python: >=3.7
Classifier: Development Status :: 4 - Beta
Classifier: Framework :: Sphinx :: Extension
Classifier: Intended Audience :: Developers
Classifier: License :: OSI Approved :: MIT License
Classifier: Programming Language :: Python :: 3
Classifier: Programming Language :: Python :: 3.8
Classifier: Programming Language :: Python :: 3.9
Classifier: Programming Language :: Python :: 3.10
Classifier: Programming Language :: Python :: Implementation :: CPython
Classifier: Topic :: Software Development :: Libraries :: Python Modules
Classifier: Topic :: Text Processing :: Markup
Classifier: Topic :: Text Processing :: Markup :: Markdown
Classifier: Topic :: Text Processing :: Markup :: reStructuredText
Requires-Dist: sphinx>=5,<7
Requires-Dist: furo>=2022.06.04 ; extra == "theme_furo"
Requires-Dist: pydata-sphinx-theme ; extra == "theme_pydata"
Requires-Dist: sphinx-rtd-theme ; extra == "theme_rtd"
Requires-Dist: sphinx-book-theme ; extra == "theme_sbt"
Project-URL: Documentation, https://sphinx-design2.readthedocs.io
Project-URL: Homepage, https://github.com/chrisj_sewell/sphinx-design2
Provides-Extra: theme_furo
Provides-Extra: theme_pydata
Provides-Extra: theme_rtd
Provides-Extra: theme_sbt
